fedpydeseq2_datasets/__init__.py
fedpydeseq2_datasets/aggregate_raw_data.py
fedpydeseq2_datasets/assets/tcga/description.md
fedpydeseq2_datasets/assets/tcga/opener.py
fedpydeseq2_datasets/constants.py
fedpydeseq2_datasets/create_reference_dds.py
fedpydeseq2_datasets/download_data/README.md
fedpydeseq2_datasets/download_data/__init__.py
fedpydeseq2_datasets/download_data/assets/centers.csv
fedpydeseq2_datasets/download_data/assets/ncomms9971-s2.xlsx
fedpydeseq2_datasets/download_data/config/config.yaml
fedpydeseq2_datasets/download_data/config/config_luad.yaml
fedpydeseq2_datasets/download_data/download_data.py
fedpydeseq2_datasets/download_data/snakemake_env.yaml
fedpydeseq2_datasets/download_data/workflow/Snakefile
fedpydeseq2_datasets/download_data/workflow/envs/python.yaml
fedpydeseq2_datasets/download_data/workflow/envs/recount3.yaml
fedpydeseq2_datasets/download_data/workflow/rules/check_csv_data.smk
fedpydeseq2_datasets/download_data/workflow/rules/common.smk
fedpydeseq2_datasets/download_data/workflow/rules/download_data.smk
fedpydeseq2_datasets/download_data/workflow/rules/move_data.smk
fedpydeseq2_datasets/download_data/workflow/rules/parquet_check_data.smk
fedpydeseq2_datasets/download_data/workflow/schemas/config.schema.yaml
fedpydeseq2_datasets/download_data/workflow/scripts/check_recount3_metadata.py
fedpydeseq2_datasets/download_data/workflow/scripts/csvize_check_tcga_clinical_data.py
fedpydeseq2_datasets/download_data/workflow/scripts/csvize_check_tcga_tumor_purity.py
fedpydeseq2_datasets/download_data/workflow/scripts/download_recount3_cohort.R
fedpydeseq2_datasets/download_data/workflow/scripts/parquetize_check_data.py
fedpydeseq2_datasets/process_and_split_data.py
fedpydeseq2_datasets/utils.py
fedpydeseq2_datasets-0.1.0.dist-info/LICENSE
fedpydeseq2_datasets-0.1.0.dist-info/METADATA
fedpydeseq2_datasets-0.1.0.dist-info/WHEEL
fedpydeseq2_datasets-0.1.0.dist-info/entry_points.txt
fedpydeseq2_datasets-0.1.0.dist-info/RECORD
