Metadata-Version: 2.1
Name: fedpydeseq2_datasets
Version: 0.1.0
Summary: This package contains utilities to process TCGA data for fedpydeseq2.
Author: Boris MUZELLEC
Author-email: boris.muzellec@owkin.com
Requires-Python: >=3.10,<3.13
Classifier: Programming Language :: Python :: 3
Classifier: Programming Language :: Python :: 3.10
Classifier: Programming Language :: Python :: 3.11
Classifier: Programming Language :: Python :: 3.12
Requires-Dist: anndata (==0.10.8)
Requires-Dist: gitpython (==3.1.43)
Requires-Dist: loguru (==0.7.2)
Requires-Dist: numpy (==1.26.4)
Requires-Dist: pandas (==2.2.2)
Requires-Dist: pyarrow (==15.0.2)
Requires-Dist: pydeseq2 (==0.4.9)
Requires-Dist: pyyaml (>=5.1)
